{
  "contract": "13",
  "tool": "smartcheck",
  "start": 1637143000.091205,
  "end": 1637143003.1088135,
  "duration": 3.017608642578125,
  "analysis": [
    {
      "name": "SOLIDITY_ADDRESS_HARDCODED",
      "patternId": "c67a09",
      "severity": 1,
      "line": 51,
      "column": 31,
      "content": "0x0"
    },
    {
      "name": "SOLIDITY_PRAGMAS_VERSION",
      "patternId": "23fc32",
      "severity": 1,
      "line": 3,
      "column": 16,
      "content": ">="
    },
    {
      "name": "SOLIDITY_PRAGMAS_VERSION",
      "patternId": "23fc32",
      "severity": 1,
      "line": 3,
      "column": 25,
      "content": "<"
    }
  ]
}