{
  "contract": "buggy_50",
  "tool": "smartcheck",
  "start": 1637149119.747533,
  "end": 1637149122.5984592,
  "duration": 2.850926160812378,
  "analysis": [
    {
      "name": "SOLIDITY_PRAGMAS_VERSION",
      "patternId": "23fc32",
      "severity": 1,
      "line": 2,
      "column": 16,
      "content": "^"
    },
    {
      "name": "SOLIDITY_PRIVATE_MODIFIER_DONT_HIDE_DATA",
      "patternId": "5616b2",
      "severity": 1,
      "line": 10,
      "column": 18,
      "content": "private"
    },
    {
      "name": "SOLIDITY_PRIVATE_MODIFIER_DONT_HIDE_DATA",
      "patternId": "5616b2",
      "severity": 1,
      "line": 15,
      "column": 7,
      "content": "private"
    },
    {
      "name": "SOLIDITY_PRIVATE_MODIFIER_DONT_HIDE_DATA",
      "patternId": "5616b2",
      "severity": 1,
      "line": 20,
      "column": 7,
      "content": "private"
    },
    {
      "name": "SOLIDITY_PRIVATE_MODIFIER_DONT_HIDE_DATA",
      "patternId": "5616b2",
      "severity": 1,
      "line": 25,
      "column": 7,
      "content": "private"
    },
    {
      "name": "SOLIDITY_PRIVATE_MODIFIER_DONT_HIDE_DATA",
      "patternId": "5616b2",
      "severity": 1,
      "line": 41,
      "column": 7,
      "content": "private"
    },
    {
      "name": "SOLIDITY_UNCHECKED_CALL",
      "patternId": "f39eed",
      "severity": 3,
      "line": 8,
      "column": 17,
      "content": "send(1ether)"
    },
    {
      "name": "SOLIDITY_UNCHECKED_CALL",
      "patternId": "f39eed",
      "severity": 3,
      "line": 13,
      "column": 17,
      "content": "send(1ether)"
    },
    {
      "name": "SOLIDITY_UNCHECKED_CALL",
      "patternId": "f39eed",
      "severity": 3,
      "line": 18,
      "column": 17,
      "content": "send(1ether)"
    },
    {
      "name": "SOLIDITY_UNCHECKED_CALL",
      "patternId": "f39eed",
      "severity": 3,
      "line": 23,
      "column": 17,
      "content": "send(1ether)"
    },
    {
      "name": "SOLIDITY_UNCHECKED_CALL",
      "patternId": "f39eed",
      "severity": 3,
      "line": 34,
      "column": 17,
      "content": "send(1ether)"
    },
    {
      "name": "SOLIDITY_UNCHECKED_CALL",
      "patternId": "f39eed",
      "severity": 3,
      "line": 39,
      "column": 17,
      "content": "send(1ether)"
    },
    {
      "name": "SOLIDITY_UNCHECKED_CALL",
      "patternId": "f39eed",
      "severity": 3,
      "line": 44,
      "column": 17,
      "content": "send(1ether)"
    },
    {
      "name": "SOLIDITY_UNCHECKED_CALL",
      "patternId": "f39eed",
      "severity": 3,
      "line": 49,
      "column": 17,
      "content": "send(1ether)"
    },
    {
      "name": "SOLIDITY_UNCHECKED_CALL",
      "patternId": "f39eed",
      "severity": 3,
      "line": 68,
      "column": 17,
      "content": "send(1ether)"
    },
    {
      "name": "SOLIDITY_UNCHECKED_CALL",
      "patternId": "f39eed",
      "severity": 3,
      "line": 83,
      "column": 17,
      "content": "send(1ether)"
    },
    {
      "name": "SOLIDITY_UNCHECKED_CALL",
      "patternId": "f39eed",
      "severity": 3,
      "line": 93,
      "column": 17,
      "content": "send(1ether)"
    },
    {
      "name": "SOLIDITY_UNCHECKED_CALL",
      "patternId": "f39eed",
      "severity": 3,
      "line": 101,
      "column": 17,
      "content": "send(1ether)"
    },
    {
      "name": "SOLIDITY_UNCHECKED_CALL",
      "patternId": "f39eed",
      "severity": 3,
      "line": 111,
      "column": 17,
      "content": "send(1ether)"
    },
    {
      "name": "SOLIDITY_UNCHECKED_CALL",
      "patternId": "f39eed",
      "severity": 3,
      "line": 119,
      "column": 17,
      "content": "send(1ether)"
    },
    {
      "name": "SOLIDITY_UNCHECKED_CALL",
      "patternId": "f39eed",
      "severity": 3,
      "line": 127,
      "column": 17,
      "content": "send(1ether)"
    },
    {
      "name": "SOLIDITY_UNCHECKED_CALL",
      "patternId": "f39eed",
      "severity": 3,
      "line": 135,
      "column": 17,
      "content": "send(1ether)"
    },
    {
      "name": "SOLIDITY_VISIBILITY",
      "patternId": 910067,
      "severity": 1,
      "line": 138,
      "column": 4,
      "content": "functionsetmanager(addresspayable"
    },
    {
      "name": "SOLIDITY_VISIBILITY",
      "patternId": "b51ce0",
      "severity": 1,
      "line": 36,
      "column": 2,
      "content": "mapping(bytes32=>HashRegistration[])HashList;"
    },
    {
      "name": "SOLIDITY_VISIBILITY",
      "patternId": "b51ce0",
      "severity": 1,
      "line": 140,
      "column": 8,
      "content": "require(newmngr."
    },
    {
      "name": "SOLIDITY_VISIBILITY",
      "patternId": "b51ce0",
      "severity": 1,
      "line": 140,
      "column": 24,
      "content": "balance>0);"
    },
    {
      "name": "SOLIDITY_VISIBILITY",
      "patternId": "b51ce0",
      "severity": 1,
      "line": 141,
      "column": 8,
      "content": "manager=newmngr;"
    }
  ]
}