{
  "contract": "buggy_26",
  "tool": "smartcheck",
  "start": 1637146573.1867883,
  "end": 1637146576.2699018,
  "duration": 3.083113431930542,
  "analysis": [
    {
      "name": "SOLIDITY_ADDRESS_HARDCODED",
      "patternId": "adc165",
      "severity": 1,
      "line": 112,
      "column": 18,
      "content": "0x0e475cd2c1f8222868cf85B4f97D7EB70fB3ffD3"
    },
    {
      "name": "SOLIDITY_ERC20_APPROVE",
      "patternId": "af782c",
      "severity": 2,
      "line": 214,
      "column": 4,
      "content": "functionapprove(addressspender,uint256value)publicreturns(bool){_approve(msg.sender,spender,value);returntrue;}"
    },
    {
      "name": "SOLIDITY_PRAGMAS_VERSION",
      "patternId": "23fc32",
      "severity": 1,
      "line": 3,
      "column": 16,
      "content": "^"
    },
    {
      "name": "SOLIDITY_PRIVATE_MODIFIER_DONT_HIDE_DATA",
      "patternId": "5616b2",
      "severity": 1,
      "line": 65,
      "column": 31,
      "content": "private"
    },
    {
      "name": "SOLIDITY_PRIVATE_MODIFIER_DONT_HIDE_DATA",
      "patternId": "5616b2",
      "severity": 1,
      "line": 76,
      "column": 52,
      "content": "private"
    },
    {
      "name": "SOLIDITY_PRIVATE_MODIFIER_DONT_HIDE_DATA",
      "patternId": "5616b2",
      "severity": 1,
      "line": 81,
      "column": 10,
      "content": "private"
    },
    {
      "name": "SOLIDITY_PRIVATE_MODIFIER_DONT_HIDE_DATA",
      "patternId": "5616b2",
      "severity": 1,
      "line": 86,
      "column": 9,
      "content": "private"
    },
    {
      "name": "SOLIDITY_PRIVATE_MODIFIER_DONT_HIDE_DATA",
      "patternId": "5616b2",
      "severity": 1,
      "line": 95,
      "column": 9,
      "content": "private"
    },
    {
      "name": "SOLIDITY_PRIVATE_MODIFIER_DONT_HIDE_DATA",
      "patternId": "5616b2",
      "severity": 1,
      "line": 106,
      "column": 8,
      "content": "private"
    },
    {
      "name": "SOLIDITY_REDUNDANT_FALLBACK_REJECT",
      "patternId": "b85a32",
      "severity": 1,
      "line": 290,
      "column": 32,
      "content": "{revert();}"
    },
    {
      "name": "SOLIDITY_SAFEMATH",
      "patternId": "837cac",
      "severity": 1,
      "line": 60,
      "column": 4,
      "content": "usingSafeMathforuint256;"
    },
    {
      "name": "SOLIDITY_UINT_CANT_BE_NEGATIVE",
      "patternId": "733fdd",
      "severity": 2,
      "line": 90,
      "column": 12,
      "content": "balances_intou26[msg.sender]-_value>=0"
    },
    {
      "name": "SOLIDITY_UINT_CANT_BE_NEGATIVE",
      "patternId": "733fdd",
      "severity": 2,
      "line": 121,
      "column": 12,
      "content": "balances_intou10[msg.sender]-_value>=0"
    },
    {
      "name": "SOLIDITY_UINT_CANT_BE_NEGATIVE",
      "patternId": "733fdd",
      "severity": 2,
      "line": 154,
      "column": 12,
      "content": "balances_intou22[msg.sender]-_value>=0"
    },
    {
      "name": "SOLIDITY_UINT_CANT_BE_NEGATIVE",
      "patternId": "733fdd",
      "severity": 2,
      "line": 187,
      "column": 12,
      "content": "balances_intou2[msg.sender]-_value>=0"
    },
    {
      "name": "SOLIDITY_UINT_CANT_BE_NEGATIVE",
      "patternId": "733fdd",
      "severity": 2,
      "line": 208,
      "column": 12,
      "content": "balances_intou18[msg.sender]-_value>=0"
    },
    {
      "name": "SOLIDITY_UINT_CANT_BE_NEGATIVE",
      "patternId": "733fdd",
      "severity": 2,
      "line": 255,
      "column": 12,
      "content": "balances_intou14[msg.sender]-_value>=0"
    },
    {
      "name": "SOLIDITY_VISIBILITY",
      "patternId": "b51ce0",
      "severity": 1,
      "line": 87,
      "column": 2,
      "content": "mapping(address=>uint)balances_intou26;"
    },
    {
      "name": "SOLIDITY_VISIBILITY",
      "patternId": "b51ce0",
      "severity": 1,
      "line": 118,
      "column": 2,
      "content": "mapping(address=>uint)balances_intou10;"
    },
    {
      "name": "SOLIDITY_VISIBILITY",
      "patternId": "b51ce0",
      "severity": 1,
      "line": 151,
      "column": 0,
      "content": "mapping(address=>uint)balances_intou22;"
    },
    {
      "name": "SOLIDITY_VISIBILITY",
      "patternId": "b51ce0",
      "severity": 1,
      "line": 184,
      "column": 0,
      "content": "mapping(address=>uint)balances_intou2;"
    },
    {
      "name": "SOLIDITY_VISIBILITY",
      "patternId": "b51ce0",
      "severity": 1,
      "line": 205,
      "column": 0,
      "content": "mapping(address=>uint)balances_intou18;"
    },
    {
      "name": "SOLIDITY_VISIBILITY",
      "patternId": "b51ce0",
      "severity": 1,
      "line": 252,
      "column": 0,
      "content": "mapping(address=>uint)balances_intou14;"
    }
  ]
}